gspoty/__init__.py
gspoty/__main__.py
gspoty-0.0.1.dist-info/LICENSE
gspoty-0.0.1.dist-info/METADATA
gspoty-0.0.1.dist-info/WHEEL
gspoty-0.0.1.dist-info/top_level.txt
gspoty-0.0.1.dist-info/RECORD
