Metadata-Version: 2.1
Name: gspoty
Version: 0.0.1
Summary: A spotify list extractor
Home-page: https://github.com/diegocrzt/gspoty
Author: Diego Ramírez
Author-email: diegocrzt@gmail.com
License: UNKNOWN
Platform: UNKNOWN
Classifier: Programming Language :: Python :: 3
Classifier: License :: OSI Approved :: MIT License
Classifier: Operating System :: OS Independent
Requires-Python: >=3.6
